{
  "history": [
    {
      "epoch": 1,
      "train_loss": 1.4284670303945672,
      "train_acc": 0.3961187214611872,
      "val_loss": 1.0860733016926976,
      "val_acc": 0.5935828877005348
    },
    {
      "epoch": 2,
      "train_loss": 0.9567406104035574,
      "train_acc": 0.6484018264840182,
      "val_loss": 0.823554046013776,
      "val_acc": 0.7219251336898396
    },
    {
      "epoch": 3,
      "train_loss": 0.7893784794633247,
      "train_acc": 0.7328767123287672,
      "val_loss": 0.7597771181779749,
      "val_acc": 0.7486631016042781
    },
    {
      "epoch": 4,
      "train_loss": 0.7091873018708947,
      "train_acc": 0.7534246575342466,
      "val_loss": 0.6739366271279075,
      "val_acc": 0.7540106951871658
    },
    {
      "epoch": 5,
      "train_loss": 0.6559820037726398,
      "train_acc": 0.769406392694064,
      "val_loss": 0.6518267906285862,
      "val_acc": 0.7379679144385026
    },
    {
      "epoch": 6,
      "train_loss": 0.6297798284656926,
      "train_acc": 0.7728310502283106,
      "val_loss": 0.6107845118339049,
      "val_acc": 0.7700534759358288
    },
    {
      "epoch": 7,
      "train_loss": 0.5611278768543784,
      "train_acc": 0.8025114155251142,
      "val_loss": 0.586530314728538,
      "val_acc": 0.7914438502673797
    },
    {
      "epoch": 8,
      "train_loss": 0.5651586654523736,
      "train_acc": 0.8047945205479452,
      "val_loss": 0.607146320177272,
      "val_acc": 0.7433155080213903
    },
    {
      "epoch": 9,
      "train_loss": 0.5523732173932742,
      "train_acc": 0.7968036529680366,
      "val_loss": 0.5719765714783082,
      "val_acc": 0.7914438502673797
    },
    {
      "epoch": 10,
      "train_loss": 0.5330508596276584,
      "train_acc": 0.8139269406392694,
      "val_loss": 0.5637369691369368,
      "val_acc": 0.7754010695187166
    }
  ],
  "classes": [
    "daisy",
    "dandelion",
    "roses",
    "sunflowers",
    "tulips"
  ],
  "best_val_acc": 0.7914438502673797,
  "test_accuracy": 0.7700534759358288,
  "classification_report": {
    "daisy": {
      "precision": 0.7567567567567568,
      "recall": 0.6511627906976745,
      "f1-score": 0.7,
      "support": 43.0
    },
    "dandelion": {
      "precision": 0.7027027027027027,
      "recall": 0.8666666666666667,
      "f1-score": 0.7761194029850746,
      "support": 30.0
    },
    "roses": {
      "precision": 0.6470588235294118,
      "recall": 0.7096774193548387,
      "f1-score": 0.676923076923077,
      "support": 31.0
    },
    "sunflowers": {
      "precision": 0.925,
      "recall": 0.8409090909090909,
      "f1-score": 0.8809523809523809,
      "support": 44.0
    },
    "tulips": {
      "precision": 0.7948717948717948,
      "recall": 0.7948717948717948,
      "f1-score": 0.7948717948717948,
      "support": 39.0
    },
    "accuracy": 0.7700534759358288,
    "macro avg": {
      "precision": 0.7652780155721333,
      "recall": 0.7726575525000131,
      "f1-score": 0.7657733311464654,
      "support": 187.0
    },
    "weighted avg": {
      "precision": 0.7774355355670234,
      "recall": 0.7700534759358288,
      "f1-score": 0.7707492098185688,
      "support": 187.0
    }
  }
}